nameparser/__init__.pyi
nameparser/py.typed
types_nameparser-0.3.2.dist-info/METADATA
types_nameparser-0.3.2.dist-info/WHEEL
types_nameparser-0.3.2.dist-info/top_level.txt
types_nameparser-0.3.2.dist-info/RECORD
