Metadata-Version: 2.4
Name: types-nameparser
Version: 0.3.2
Summary: Typing stubs for the nameparser library
Author-email: Lucian Buzzo <lucian.buzzo@gmail.com>
Maintainer-email: Lucian Buzzo <lucian.buzzo@gmail.com>
License: MIT
Keywords: typing,stubs,nameparser,type-hints
Classifier: Development Status :: 4 - Beta
Classifier: Intended Audience :: Developers
Classifier: License :: OSI Approved :: MIT License
Classifier: Operating System :: OS Independent
Classifier: Programming Language :: Python :: 3
Classifier: Programming Language :: Python :: 3.8
Classifier: Programming Language :: Python :: 3.9
Classifier: Programming Language :: Python :: 3.10
Classifier: Programming Language :: Python :: 3.11
Classifier: Programming Language :: Python :: 3.12
Classifier: Topic :: Software Development :: Libraries :: Python Modules
Classifier: Topic :: Software Development :: Quality Assurance
Classifier: Typing :: Stubs Only
Requires-Python: >=3.8
